{
  "id": "ru-0329",
  "title": "Астрономические явления",
  "difficulty": "easy",
  "meta": {
    "theme": "Явления в астрономии",
    "batch": "ru-batch-13",
    "difficultyScore": 34,
    "editorialRank": 61,
    "gptDifficulty": 79,
    "gptRationale": "Здесь смешаны явления, объекты и классы космических объектов, поэтому игроку мешают и научная терминология, и неоднородность групп."
  },
  "groups": [
    {
      "id": "eclipse_types",
      "label": "Затмения",
      "items": [
        "Солнечное затмение",
        "Лунное затмение",
        "Кольцеобразное",
        "Гибридное"
      ]
    },
    {
      "id": "sky_phenomena",
      "label": "Небесные явления",
      "items": [
        "Метеорный поток",
        "Полярное сияние",
        "Суперлуние",
        "Транзит Меркурия"
      ]
    },
    {
      "id": "star_events",
      "label": "Космические объекты",
      "items": [
        "Белый карлик",
        "Пульсар",
        "Квазар",
        "Нейтронная звезда"
      ]
    },
    {
      "id": "galaxy_features",
      "label": "Галактики",
      "items": [
        "Млечный путь",
        "Туманность Андромеды",
        "Магеллановы облака",
        "Треугольник"
      ]
    }
  ]
}
