{
  "id": "ru-0464",
  "title": "Виды покрытий дорог",
  "difficulty": "easy",
  "meta": {
    "theme": "Дорожное строительство и покрытия",
    "batch": "ru-batch-20",
    "difficultyScore": 28,
    "editorialRank": 48,
    "gptDifficulty": 61,
    "gptRationale": "Это уже смесь дорожной и инженерной инфраструктуры, где названия развязок и мостов знают не все."
  },
  "groups": [
    {
      "id": "road_surface_types",
      "label": "Покрытия дорог",
      "items": [
        "Асфальт",
        "Бетон",
        "Брусчатка",
        "Гравий"
      ]
    },
    {
      "id": "bridge_types",
      "label": "Типы мостов",
      "items": [
        "Балочный",
        "Арочный",
        "Подвесной",
        "Вантовый"
      ]
    },
    {
      "id": "tunnel_types",
      "label": "Тоннели",
      "items": [
        "Автомобильный",
        "Железнодорожный",
        "Метро",
        "Подводный"
      ]
    },
    {
      "id": "interchange_types",
      "label": "Развязки",
      "items": [
        "Кольцо",
        "Клеверный лист",
        "Трубач",
        "Ромб"
      ]
    }
  ]
}
