{
  "id": "ru-0489",
  "title": "Великая Отечественная — города",
  "difficulty": "easy",
  "meta": {
    "theme": "Города-герои и исторические места ВОВ",
    "batch": "ru-batch-21",
    "difficultyScore": 51,
    "editorialRank": 56,
    "gptDifficulty": 59,
    "gptRationale": "Военная история знакома многим, но набор смешивает статусы городов, события и места обороны, что усложняет сортировку."
  },
  "groups": [
    {
      "id": "cities_heroes",
      "label": "Города-герои",
      "items": [
        "Москва",
        "Ленинград",
        "Сталинград",
        "Севастополь"
      ]
    },
    {
      "id": "cities_heroes_2",
      "label": "Ещё города-герои",
      "items": [
        "Одесса",
        "Киев",
        "Минск",
        "Тула"
      ]
    },
    {
      "id": "liberation_dates",
      "label": "Освобождённые города",
      "items": [
        "Берлин 1945",
        "Варшава 1945",
        "Прага 1945",
        "Будапешт 1945"
      ]
    },
    {
      "id": "sieges",
      "label": "Осады и блокады",
      "items": [
        "Блокада Ленинграда",
        "Оборона Москвы",
        "Брестская крепость",
        "Осада Сталинграда"
      ]
    }
  ]
}
