{
  "id": "ru-0301",
  "title": "Гормоны",
  "difficulty": "medium",
  "meta": { "theme": "Гормоны и их функции", "batch": "ru-batch-12" },
  "groups": [
    { "id": "stress_hormones", "label": "Стресс", "revealHint": "СТРЕСС", "items": ["Кортизол", "Адреналин", "Норадреналин", "Кортикотропин"] },
    { "id": "happy_hormones", "label": "Счастье", "revealHint": "СЧАСТЬЕ", "items": ["Серотонин", "Дофамин", "Эндорфин", "Окситоцин"] },
    { "id": "sex_hormones", "label": "Половые гормоны", "revealHint": "ПОЛОВЫЕ", "items": ["Тестостерон", "Эстроген", "Прогестерон", "Пролактин"] },
    { "id": "metabolic_hormones", "label": "Обмен веществ", "revealHint": "МЕТАБОЛИЗМ", "items": ["Инсулин", "Глюкагон", "Лептин", "Грелин"] }
  ]
}
