{
  "id": "ru-0153",
  "title": "Кухонная техника",
  "difficulty": "easy",
  "meta": { "theme": "Кухонная техника", "batch": "ru-batch-04" },
  "groups": [
    { "id": "heating", "label": "Тепловая", "items": ["Духовка", "Микроволновка", "Мультиварка", "Аэрогриль"] },
    { "id": "cooling", "label": "Холодная", "items": ["Холодильник", "Морозильник", "Винный шкаф", "Ледогенератор"] },
    { "id": "prep", "label": "Приготовление", "items": ["Блендер", "Миксер", "Кухонный комбайн", "Слайсер"] },
    { "id": "drinks_tech", "label": "Для напитков", "items": ["Кофемашина", "Чайник", "Соковыжималка", "Термопот"] }
  ]
}
