{
  "id": "ru-0476",
  "title": "Домашние животные",
  "difficulty": "easy",
  "meta": {
    "theme": "Популярные домашние питомцы",
    "batch": "ru-batch-20",
    "difficultyScore": 13,
    "editorialRank": 12,
    "gptDifficulty": 11,
    "gptRationale": "Домашние животные и их подвиды максимально бытовые, с очень ясными и привычными категориями."
  },
  "groups": [
    {
      "id": "classic_pets",
      "label": "Классические",
      "items": [
        "Кошка",
        "Собака",
        "Кролик",
        "Хомяк"
      ]
    },
    {
      "id": "feathered_pets",
      "label": "Пернатые",
      "items": [
        "Попугай волнистый",
        "Канарейка",
        "Корелла",
        "Амадина"
      ]
    },
    {
      "id": "aquatic_pets",
      "label": "Аквариумные",
      "items": [
        "Золотая рыбка",
        "Гуппи",
        "Скалярия",
        "Петушок"
      ]
    },
    {
      "id": "exotic_pets",
      "label": "Экзотические",
      "items": [
        "Черепаха",
        "Игуана",
        "Тарантул",
        "Сумч. летяга"
      ]
    }
  ]
}
