{
  "id": "ru-0272",
  "title": "Религиозные праздники",
  "difficulty": "easy",
  "meta": {
    "theme": "Религиозные праздники",
    "batch": "ru-batch-10",
    "difficultyScore": 15,
    "editorialRank": 46,
    "gptDifficulty": 66,
    "gptRationale": "Religious holidays are concrete yet strongly culture-dependent, and distinguishing names across four traditions is fairly demanding."
  },
  "groups": [
    {
      "id": "orthodox_feasts",
      "label": "Православные",
      "items": [
        "Пасха",
        "Рождество",
        "Крещение",
        "Троица"
      ]
    },
    {
      "id": "muslim_feasts",
      "label": "Мусульманские",
      "items": [
        "Ид аль-Фитр",
        "Ид аль-Адха",
        "Рамадан",
        "Ашура"
      ]
    },
    {
      "id": "jewish_feasts",
      "label": "Иудейские",
      "items": [
        "Песах",
        "Ханука",
        "Рош ха-Шана",
        "Йом Кипур"
      ]
    },
    {
      "id": "hindu_feasts",
      "label": "Индуистские",
      "items": [
        "Дивали",
        "Холи",
        "Дасера",
        "Наваратри"
      ]
    }
  ]
}
